y0_bio/__init__.py
y0_bio/__main__.py
y0_bio/cli.py
y0_bio/version.py
y0_bio/io/__init__.py
y0_bio/io/bel.py
y0_bio/resources/__init__.py
y0_bio/resources/covid_example.bel.nodelink.json
y0_bio-0.0.1.dist-info/LICENSE
y0_bio-0.0.1.dist-info/METADATA
y0_bio-0.0.1.dist-info/WHEEL
y0_bio-0.0.1.dist-info/entry_points.txt
y0_bio-0.0.1.dist-info/top_level.txt
y0_bio-0.0.1.dist-info/RECORD
