Metadata-Version: 2.1
Name: y0-bio
Version: 0.0.1
Summary: Biological applications of y0
Home-page: https://github.com/y0-causal-inference/y0-bio
Author: Charles Tapley Hoyt
Author-email: cthoyt@gmail.com
Maintainer: Charles Tapley Hoyt
Maintainer-email: cthoyt@gmail.com
License: MIT
Download-URL: https://github.com/y0-causal-inference/y0-bio/releases
Project-URL: Bug Tracker, https://github.com/y0-causal-inference/y0-bio/issues
Project-URL: Source Code, https://github.com/y0-causal-inference/y0-bio
Keywords: cthoyt,cookiecutter
Platform: UNKNOWN
Classifier: Development Status :: 1 - Planning
Classifier: Environment :: Console
Classifier: Intended Audience :: Developers
Classifier: License :: OSI Approved :: MIT License
Classifier: Operating System :: OS Independent
Classifier: Framework :: Pytest
Classifier: Framework :: tox
Classifier: Framework :: Sphinx
Classifier: Programming Language :: Python
Classifier: Programming Language :: Python :: 3.8
Classifier: Programming Language :: Python :: 3.9
Classifier: Programming Language :: Python :: 3 :: Only
Requires-Python: >=3.8
Requires-Dist: more-itertools
Requires-Dist: tqdm
Requires-Dist: click
Requires-Dist: more-click
Requires-Dist: y0 (>=0.0.3)
Requires-Dist: pybel
Requires-Dist: indra
Provides-Extra: docs
Requires-Dist: sphinx ; extra == 'docs'
Requires-Dist: sphinx-rtd-theme ; extra == 'docs'
Requires-Dist: sphinx-click ; extra == 'docs'
Requires-Dist: sphinx-autodoc-typehints ; extra == 'docs'
Requires-Dist: sphinx-automodapi ; extra == 'docs'
Requires-Dist: texext ; extra == 'docs'
